{"id": "ahi", "age": "33", "dob": "", "bn": {"name": "মোঃ মিলন", "birthPlace": "ঝাটরা,দুমকি,পটুয়াখালী।", "profession": "", "bio": "", "cause": "ওই দিন সকালে মিলন মাছ আনার উদ্দেশ্যো বাসা থেকে বের হয়ে চিটাগাং রোড এলাকায় যান। এরপর ফোন আসে মিলনের মরদেহ পড়ে আছে মহাসড়কের উপর। কিছুক্ষণ পর তার পরিচিত লোকজন লাশ দেখতে পেয়ে খবর দেয় পরিবারকে। তাতক্ষনিকভাবে পরিবারের সদস্যরা মরদেহ উদ্ধার করে নিয়ে আসে সিদ্ধিরগঞ্জ পুলস্থ তার বাসায়।"}, "en": {"name": "Md. Milon", "birthPlace": "DUMKI, PATUAKHALI.", "profession": "Businessman", "bio": "", "cause": "That morning, Milon left his house to get fish and went to the Chittagong Road area. Later, a call came saying that Milon's body was lying on the highway. Shortly after, his acquaintances saw the body and informed the family. Immediately, the family members retrieved the body and brought it to his house near Siddhirganj Bridge."}}