{"id": "aip", "age": "28", "dob": "", "bn": {"name": "মোঃ জোনায়েদ।", "birthPlace": "হাসনাবাদ পূর্ব পাড়া, রায়পুরা, নরসিংদী।", "profession": "", "bio": "", "cause": "মিরপুর ১০ গোলচত্বরে পুলিশের গুলিতে গুলিবিদ্ধ হন।পরে স্থানীয় একটি হাসপাতালে শেষ নিশ্বাস ত্যাগ করেন।"}, "en": {"name": "Md. Jonayed.", "birthPlace": "Hasnabad Purba Para, Raipura, Narsingdi.", "profession": "", "bio": "", "cause": "He was shot in police firing at Mirpur 10 Roundabout. He later breathed his last breath at a local hospital."}}