{
  "id": "apw",
  "age": "12",
  "dob": "",
  "date": "23rd December, 2024",
  "bn": {
    "name": "মো. আরাফাত",
    "info": "৫ই আগস্ট গুলিবিদ্ধ হয়ে চিকিৎসাধীন ছিলেন",
    "birthPlace": "",
    "profession": "মাদরাসা শিক্ষার্থী",
    "bio": "নাজেরা শেষ করে তিন পারা কোরআন মুখস্থ করা আরাফাত উত্তরা জামিয়া রওজাতুল উলুম মাদরাসার ইবতেদায়ি আউয়ালের শিক্ষার্থী ছিলেন।\n৫ আগস্ট উত্তরা আজমপুরে আন্দোলনের সময় গুলিবিদ্ধ হন। আধুনিক হাসপাতাল ও কুর্মিটোলায় ফেরত পাঠানোর পর সিএমএইচে ভর্তি করা হলেও তিন মাস চিকিৎসাধীন থেকে আজ ২২ ডিসেম্বর ইন্তেকাল করেন। ইন্না-লিল্লাহি ওয়া ইন্না ইলাইহি রাজীয়ুন।\nঘাতক বুলেট আরাফাতের বাম পাজর ভেদ করে মেরুদণ্ড ভেঙে ডান দিক দিয়ে বের হয়ে যায়, ফলে একটি কিডনি নষ্ট হয়। উন্নত চিকিৎসার জন্য ২৪ ডিসেম্বর বিদেশ নেওয়ার পরিকল্পনা ছিল, কিন্তু তার আগেই শহীদ হন। আল্লাহ শহীদ আরাফাতকে জান্নাত নসিব করুন।",
    "cause": "গুলিবিদ্ধ"
  },
  "en": {
    "name": "Md. Arafat",
    "info": "He was under treatment since 5th August",
    "birthPlace": "",
    "profession": "Madrasa Student",
    "bio": "After completing Nazera and memorizing three parts of the Quran, Arafat was a student of Ibtedaayi Awal at Uttara Jamia Rawjatul Uloom Madrasa.\nOn August 5, he was shot during the movement in Azampur, Uttara. Despite being admitted to CMH after being referred back from Modern Hospital and Kurmitola, he passed away today, December 22, after three months of treatment. Inna-Lillahi wa inna ilayhi raji'un.\nThe fatal bullet pierced Arafat's left rib, breaking his spine and exiting through the right side, causing one kidney to fail. There was a plan to take him abroad for advanced treatment on December 24, but he was martyred before that. May Allah grant martyr Arafat Jannah.",
    "cause": "Shot"
  }
}
